kfilter/__init__.py
kfilter/kalman.py
kfilter/simplify.py
kfilter-1.1.0.dist-info/DESCRIPTION.rst
kfilter-1.1.0.dist-info/METADATA
kfilter-1.1.0.dist-info/RECORD
kfilter-1.1.0.dist-info/WHEEL
kfilter-1.1.0.dist-info/metadata.json
kfilter-1.1.0.dist-info/top_level.txt
