Metadata-Version: 2.0
Name: kfilter
Version: 1.1.0
Summary: Kalman filter
Home-page: https://github.com/clnrp/kfilter
Author: Cleoner Pietralonga
Author-email: cleonerp@gmail.com
License: UNKNOWN
Platform: UNKNOWN
Classifier: Development Status :: 4 - Beta
Classifier: Intended Audience :: Science/Research
Classifier: Topic :: Scientific/Engineering
Classifier: License :: OSI Approved :: Apache Software License
Classifier: Programming Language :: Python :: 2.7
Classifier: Programming Language :: Python :: 3
Classifier: Programming Language :: Python :: 3.4
Classifier: Programming Language :: Python :: 3.5
Requires-Dist: numpy
Requires-Dist: sympy
